langgraph_checkpoint_aws-1.0.1.dist-info/METADATA
langgraph_checkpoint_aws-1.0.1.dist-info/WHEEL
langgraph_checkpoint_aws-1.0.1.dist-info/entry_points.txt
langgraph_checkpoint_aws-1.0.1.dist-info/licenses/LICENSE
langgraph_checkpoint_aws/__init__.py
langgraph_checkpoint_aws/agentcore/README.md
langgraph_checkpoint_aws/agentcore/__init__.py
langgraph_checkpoint_aws/agentcore/constants.py
langgraph_checkpoint_aws/agentcore/helpers.py
langgraph_checkpoint_aws/agentcore/models.py
langgraph_checkpoint_aws/agentcore/saver.py
langgraph_checkpoint_aws/agentcore/store.py
langgraph_checkpoint_aws/agentcore/valkey/README.md
langgraph_checkpoint_aws/agentcore/valkey/__init__.py
langgraph_checkpoint_aws/agentcore/valkey/models.py
langgraph_checkpoint_aws/agentcore/valkey/saver.py
langgraph_checkpoint_aws/async_saver.py
langgraph_checkpoint_aws/async_session.py
langgraph_checkpoint_aws/cache/__init__.py
langgraph_checkpoint_aws/cache/valkey/__init__.py
langgraph_checkpoint_aws/cache/valkey/cache.py
langgraph_checkpoint_aws/checkpoint/__init__.py
langgraph_checkpoint_aws/checkpoint/dynamodb/__init__.py
langgraph_checkpoint_aws/checkpoint/dynamodb/saver.py
langgraph_checkpoint_aws/checkpoint/dynamodb/serialization.py
langgraph_checkpoint_aws/checkpoint/dynamodb/storage_strategy.py
langgraph_checkpoint_aws/checkpoint/dynamodb/unified_repository.py
langgraph_checkpoint_aws/checkpoint/dynamodb/utils.py
langgraph_checkpoint_aws/checkpoint/valkey/__init__.py
langgraph_checkpoint_aws/checkpoint/valkey/async_saver.py
langgraph_checkpoint_aws/checkpoint/valkey/base.py
langgraph_checkpoint_aws/checkpoint/valkey/saver.py
langgraph_checkpoint_aws/checkpoint/valkey/utils.py
langgraph_checkpoint_aws/constants.py
langgraph_checkpoint_aws/models.py
langgraph_checkpoint_aws/saver.py
langgraph_checkpoint_aws/session.py
langgraph_checkpoint_aws/store/__init__.py
langgraph_checkpoint_aws/store/valkey/__init__.py
langgraph_checkpoint_aws/store/valkey/async_store.py
langgraph_checkpoint_aws/store/valkey/base.py
langgraph_checkpoint_aws/store/valkey/constants.py
langgraph_checkpoint_aws/store/valkey/document_utils.py
langgraph_checkpoint_aws/store/valkey/exceptions.py
langgraph_checkpoint_aws-1.0.1.dist-info/RECORD
